ur_gym/__init__.py
ur_gym/envs/__init__.py
ur_gym/envs/ur_env.py
hj_ur5-0.0.1.dist-info/METADATA
hj_ur5-0.0.1.dist-info/WHEEL
hj_ur5-0.0.1.dist-info/top_level.txt
hj_ur5-0.0.1.dist-info/RECORD
